logmcp/__init__.py
logmcp/config.py
logmcp/logger.py
logmcp/server.py
logmcp/tools.py
logmcp/services/__init__.py
logmcp/services/loki_service.py
logmcp-1.0.2.dist-info/METADATA
logmcp-1.0.2.dist-info/WHEEL
logmcp-1.0.2.dist-info/entry_points.txt
logmcp-1.0.2.dist-info/RECORD
