Metadata-Version: 2.4
Name: logmcp
Version: 1.0.2
Summary: MCP server for log querying and system monitoring via Loki using stdio transport
Author-email: LogMCP Team <team@logmcp.com>
Requires-Python: >=3.10
Requires-Dist: fastmcp>=1.0.0
Requires-Dist: pydantic>=2.11.7
Requires-Dist: requests>=2.31.0
Provides-Extra: dev
Requires-Dist: black>=23.0.0; extra == 'dev'
Requires-Dist: isort>=5.12.0; extra == 'dev'
Requires-Dist: mypy>=1.0.0; extra == 'dev'
Requires-Dist: pytest-asyncio>=0.21.0; extra == 'dev'
Requires-Dist: pytest-mock>=3.10.0; extra == 'dev'
Requires-Dist: pytest>=7.0.0; extra == 'dev'
